README.md
setup.py
src/artnet/__init__.py
src/artnet/app.py
src/artnet/command_line.py
src/artnet/config.py
src/artnet/dataFrame.py
src/artnet/server.py
src/artnet/usergui.py
src/rasl_artnet.egg-info/PKG-INFO
src/rasl_artnet.egg-info/SOURCES.txt
src/rasl_artnet.egg-info/dependency_links.txt
src/rasl_artnet.egg-info/entry_points.txt
src/rasl_artnet.egg-info/requires.txt
src/rasl_artnet.egg-info/top_level.txt